{
    "ipeps_args": {
        "model": "J1J2",
        "lam": 0,
        "J2": 0.2,
        "ctm_symmetry": "rotational",
        "initial_state_symmetry": "rotational",
        "seed": 25,
        "D": 2,
        "dtype": "single",
        "device": "cuda",
        "noise": 0,
        "chi": 48,
        "split": false,
        "projector_mode": "qr",
        "fn_addition": "seed25",
        "use_checkpoint": true
    },
    "state": [
        -0.23587282001972198,
        0.5491644740104675,
        0.48002222180366516,
        0.14693434536457062,
        -0.048039760440588,
        0.21832188963890076,
        0.21826614439487457,
        0.14696556329727173,
        -0.05678889527916908,
        0.35112255811691284,
        0.08366820216178894,
        0.3448188602924347
    ],
    "map": [
        [
            [
                [
                    [
                        1,
                        11
                    ],
                    [
                        11,
                        3
                    ]
                ],
                [
                    [
                        11,
                        7
                    ],
                    [
                        3,
                        4
                    ]
                ]
            ],
            [
                [
                    [
                        11,
                        3
                    ],
                    [
                        7,
                        4
                    ]
                ],
                [
                    [
                        3,
                        4
                    ],
                    [
                        4,
                        0
                    ]
                ]
            ]
        ],
        [
            [
                [
                    [
                        8,
                        10
                    ],
                    [
                        10,
                        6
                    ]
                ],
                [
                    [
                        10,
                        5
                    ],
                    [
                        6,
                        9
                    ]
                ]
            ],
            [
                [
                    [
                        10,
                        6
                    ],
                    [
                        5,
                        9
                    ]
                ],
                [
                    [
                        6,
                        9
                    ],
                    [
                        9,
                        2
                    ]
                ]
            ]
        ]
    ],
    "optimization": [
        {
            "args": {
                "optimizer": "lbfgs",
                "line_search": true,
                "learning_rate": 1,
                "epochs": 500,
                "threads": 1,
                "tolerance": 1e-10,
                "warmup_steps": 20,
                "gradient_steps": 20,
                "gauge": null,
                "gauge_tolerance": 1e-10,
                "regauge_every": 10,
                "gauge_criterion": 0.1
            },
            "energies": [
                -0.4034150242805481,
                -0.5669757127761841,
                -0.5725196003913879,
                -0.5726318955421448,
                -0.5744146108627319,
                -0.5756423473358154,
                -0.5762262344360352,
                -0.5765949487686157,
                -0.5778299570083618,
                -0.5793827176094055,
                -0.5807458758354187,
                -0.5809435248374939,
                -0.5809562802314758,
                -0.580964982509613,
                -0.5809687376022339,
                -0.5809811949729919,
                -0.5809951424598694,
                -0.581018328666687,
                -0.5810242891311646,
                -0.581024706363678,
                -0.5810248851776123,
                -0.5810248851776123
            ],
            "norms": [
                null,
                null,
                null,
                null,
                null,
                null,
                null,
                null,
                null,
                null,
                null,
                null,
                null,
                null,
                null,
                null,
                null,
                null,
                null,
                null,
                null,
                null,
                null
            ]
        }
    ]
}